robohash/__init__.py
robohash/cli.py
robohash/robohash.py
robohash/webfront.py
robohash/backgrounds/bg1/000#robotBG-11.png
robohash/backgrounds/bg1/001#robotBG-12.png
robohash/backgrounds/bg1/002#final3.png
robohash/backgrounds/bg1/003#final2.png
robohash/backgrounds/bg1/004#final4.png
robohash/backgrounds/bg1/005#final5.png
robohash/backgrounds/bg1/006#final9.png
robohash/backgrounds/bg1/007#final7.png
robohash/backgrounds/bg1/008#final10.png
robohash/backgrounds/bg1/009#final6.png
robohash/backgrounds/bg1/010#final8.png
robohash/backgrounds/bg1/011#final1.png
robohash/backgrounds/bg1/012#robotBG-10.png
robohash/backgrounds/bg2/000#robotBG-06.png
robohash/backgrounds/bg2/001#robotBG-08.png
robohash/backgrounds/bg2/002#robotBG-04.png
robohash/backgrounds/bg2/003#robotBG-03.png
robohash/backgrounds/bg2/004#robotBG-01.png
robohash/backgrounds/bg2/005#robotBG-02.png
robohash/backgrounds/bg2/006#robotBG-07.png
robohash/sets/set1/blue/000#Mouth/000#blue_mouth-10.png
robohash/sets/set1/blue/000#Mouth/001#blue_mouth-07.png
robohash/sets/set1/blue/000#Mouth/002#blue_mouth-04.png
robohash/sets/set1/blue/000#Mouth/003#blue_mouth-05.png
robohash/sets/set1/blue/000#Mouth/004#blue_mouth-01.png
robohash/sets/set1/blue/000#Mouth/005#blue_mouth-02.png
robohash/sets/set1/blue/000#Mouth/006#blue_mouth-06.png
robohash/sets/set1/blue/000#Mouth/007#blue_mouth-08.png
robohash/sets/set1/blue/000#Mouth/008#blue_mouth-09.png
robohash/sets/set1/blue/000#Mouth/009#blue_mouth-03.png
robohash/sets/set1/blue/001#Eyes/000#blue_eyes-07.png
robohash/sets/set1/blue/001#Eyes/001#blue_eyes-09.png
robohash/sets/set1/blue/001#Eyes/002#blue_eyes-10.png
robohash/sets/set1/blue/001#Eyes/003#blue_eyes-02.png
robohash/sets/set1/blue/001#Eyes/004#blue_eyes-03.png
robohash/sets/set1/blue/001#Eyes/005#blue_eyes-05.png
robohash/sets/set1/blue/001#Eyes/006#blue_eyes-06.png
robohash/sets/set1/blue/001#Eyes/007#blue_eyes-01.png
robohash/sets/set1/blue/001#Eyes/008#blue_eyes-08.png
robohash-2.0.dist-info/licenses/LICENSE.txt
robohash-2.0.dist-info/METADATA
robohash-2.0.dist-info/WHEEL
robohash-2.0.dist-info/top_level.txt
robohash-2.0.dist-info/RECORD
