Metadata-Version: 2.4
Name: robohash
Version: 2.0
Summary: One of the leading robot-based hashing tools on the web
Author-email: e1ven <robo@robohash.org>
License: MIT
Project-URL: Homepage, https://github.com/e1ven/Robohash
Project-URL: Repository, https://github.com/e1ven/Robohash
Project-URL: Docker Images, https://github.com/e1ven/Robohash/pkgs/container/robohash
Keywords: robots,avatar,identicon
Classifier: Programming Language :: Python :: 3
Classifier: Programming Language :: Python :: 3.8
Classifier: Programming Language :: Python :: 3.9
Classifier: Programming Language :: Python :: 3.10
Classifier: Programming Language :: Python :: 3.11
Classifier: Programming Language :: Python :: 3.12
Classifier: Development Status :: 5 - Production/Stable
Classifier: Intended Audience :: Developers
Classifier: Topic :: Internet :: WWW/HTTP :: Dynamic Content
Classifier: Topic :: Multimedia :: Graphics
Classifier: Topic :: Software Development :: Libraries :: Python Modules
Classifier: Topic :: Utilities
Requires-Python: >=3.8
License-File: LICENSE.txt
Requires-Dist: pillow>=9.1.1
Requires-Dist: natsort>=8.1.0
Provides-Extra: web
Requires-Dist: tornado>=6.1; extra == "web"
Dynamic: license-file
